timeseries_cleaner/__init__.py
timeseries_cleaner/cleaner.py
timeseries_cleaner/loader.py
timeseries_cleaner/merger.py
timeseries_cleaner/splitter.py
lift_timeseries_cleaner-0.1.1.dist-info/METADATA
lift_timeseries_cleaner-0.1.1.dist-info/WHEEL
lift_timeseries_cleaner-0.1.1.dist-info/licenses/LICENSE
lift_timeseries_cleaner-0.1.1.dist-info/RECORD
