Metadata-Version: 2.4
Name: lift_timeseries_cleaner
Version: 0.1.1
Summary: A small library to preprocess diary/transaction data for time series models.
Project-URL: Homepage, https://example.com/timeseries-cleaner
Author-email: John Kamau <kkamaujohn@gmail.com>
License-Expression: MIT
License-File: LICENSE
Classifier: Operating System :: OS Independent
Classifier: Programming Language :: Python :: 3
Requires-Python: >=3.7
Requires-Dist: pandas>=1.0.0
